MANIFEST.in
README.md
setup.py
interaction_engine/__init__.py
interaction_engine/engine.py
interaction_engine.egg-info/PKG-INFO
interaction_engine.egg-info/SOURCES.txt
interaction_engine.egg-info/dependency_links.txt
interaction_engine.egg-info/requires.txt
interaction_engine.egg-info/top_level.txt
interaction_engine/interfaces/__init__.py
interaction_engine/interfaces/interface.py
interaction_engine/interfaces/terminal_interface.py
interaction_engine/messager/__init__.py
interaction_engine/messager/base_messenger.py
interaction_engine/messager/convenience.py
interaction_engine/messager/directed_graph.py
interaction_engine/messager/message.py
interaction_engine/messager/node.py
interaction_engine/planner/__init__.py
interaction_engine/planner/base_planner.py
interaction_engine/planner/messanger_planner.py
interaction_engine/text_populator/__init__.py
interaction_engine/text_populator/base_populator.py
interaction_engine/text_populator/database_populator.py
interaction_engine/text_populator/populator.py
interaction_engine/text_populator/variety_populator.py