Metadata-Version: 2.1
Name: interaction-engine
Version: 0.0.4
Summary: A framework for turn-taking interactions
Home-page: https://github.com/robotpt/interaction-engine
Author: Audrow Nash
Author-email: audrowna@usc.edu
License: MIT
Platform: UNKNOWN
Classifier: License :: OSI Approved :: MIT License
Classifier: Programming Language :: Python
Classifier: Programming Language :: Python :: 3
Classifier: Programming Language :: Python :: 3.6
Classifier: Programming Language :: Python :: Implementation :: CPython
Classifier: Programming Language :: Python :: Implementation :: PyPy
Requires-Python: >=3.6.0
